pyferris-0.5.2.dist-info/METADATA
pyferris-0.5.2.dist-info/WHEEL
pyferris-0.5.2.dist-info/licenses/LICENSE
pyferris/__init__.py
pyferris/_pyferris.pypy311-pp73-s390x-linux-gnu.so
pyferris/async_ops.py
pyferris/cache.py
pyferris/concurrent.py
pyferris/config.py
pyferris/core.py
pyferris/distributed.py
pyferris/executor.py
pyferris/io/__init__.py
pyferris/io/csv.py
pyferris/io/file_reader.py
pyferris/io/file_writer.py
pyferris/io/json.py
pyferris/io/parallel_io.py
pyferris/io/simple_io.py
pyferris/memory.py
pyferris/pipeline.py
pyferris/py.typed
pyferris/safe_thread.py
pyferris/scheduler.py
pyferris/shared_memory.py
pyferris-0.5.2.dist-info/RECORD
