Metadata-Version: 2.4
Name: pyferris
Version: 0.5.2
Classifier: Development Status :: 3 - Alpha
Classifier: Intended Audience :: Developers
Classifier: License :: OSI Approved :: MIT License
Classifier: Operating System :: OS Independent
Classifier: Programming Language :: Python :: 3
Classifier: Programming Language :: Python :: 3.10
Classifier: Programming Language :: Python :: 3.11
Classifier: Programming Language :: Python :: 3.12
Classifier: Programming Language :: Python :: 3.13
Classifier: Programming Language :: Python :: Implementation :: PyPy
Classifier: Programming Language :: Python :: Implementation :: CPython
Classifier: Programming Language :: Python
Classifier: Programming Language :: Rust
License-File: LICENSE
Summary: PyFerris is a high-performance parallel processing library for Python, powered by Rust and PyO3
Author-email: Dang Van Nghiem <vannghiem848@gmail.com>
Requires-Python: >=3.10
